python3_shodan/__init__.py
python3_shodan-0.0.1.dist-info/METADATA
python3_shodan-0.0.1.dist-info/WHEEL
python3_shodan-0.0.1.dist-info/top_level.txt
python3_shodan-0.0.1.dist-info/RECORD
